src/app.py
jira_buddy-0.0.1.dist-info/METADATA
jira_buddy-0.0.1.dist-info/WHEEL
jira_buddy-0.0.1.dist-info/entry_points.txt
jira_buddy-0.0.1.dist-info/licenses/LICENSE
jira_buddy-0.0.1.dist-info/RECORD
