Metadata-Version: 2.4
Name: jira-buddy
Version: 0.0.1
Summary: A python tool to interact with Jira
Author-email: nbr23 <max@23.tf>
License-Expression: MIT
License-File: LICENSE
Requires-Python: >=3.13
Requires-Dist: requests
Provides-Extra: dev
Requires-Dist: black; extra == 'dev'
Requires-Dist: pytest; extra == 'dev'
Requires-Dist: ruff; extra == 'dev'
